omekac_iiif_tools/__init__.py
omekac_iiif_tools/_modidx.py
omekac_iiif_tools/core.py
omekac_iiif_tools-0.0.2.dist-info/LICENSE
omekac_iiif_tools-0.0.2.dist-info/METADATA
omekac_iiif_tools-0.0.2.dist-info/WHEEL
omekac_iiif_tools-0.0.2.dist-info/entry_points.txt
omekac_iiif_tools-0.0.2.dist-info/top_level.txt
omekac_iiif_tools-0.0.2.dist-info/RECORD
